{
  "schemaVersion": 3,
  "order": 51,
  "id": "dark-spear-01",
  "name": "DarkSpear01",
  "category": "weapon",
  "rarity": null,
  "stars": 3,
  "evolvedStars": 4,
  "element": null,
  "weaponType": "Spear",
  "stats": {
    "atk": 368,
    "hp": 2310,
    "spd": null,
    "cost": 9
  },
  "image": "https://ik.imagekit.io/r8fsa98s9/weapons/DarkSpear01.png",
  "refs": {
    "activeSkills": [],
    "passives": [
      "HasteUp4User1KillPlus"
    ],
    "activeSkillsAI": {},
    "aiSequence": null,
    "leaderBuff": null,
    "leaderBuffCondition": null,
    "summonableMonsters": null
  },
  "resolved": {
    "activeSkills": {},
    "passives": {
      "HasteUp4User1KillPlus": {
        "id": "HasteUp4User1KillPlus",
        "found": false
      }
    },
    "activeSkillsAI": {},
    "aiSequence": null,
    "leaderCondition": null
  },
  "effect": null,
  "profile": null,
  "internal": {
    "sourceId": "DarkSpear01",
    "family": "DarkSpear",
    "source": "apk_extract",
    "treatAsDuplicateOf": null
  },
  "raw": {
    "name": "DarkSpear01",
    "family": "DarkSpear",
    "class": "Weapon",
    "passives": {
      "0": "HasteUp4User1KillPlus"
    },
    "stars": 3,
    "evolvedStars": 4,
    "baseAttack": 368,
    "baseMaxHp": 2310,
    "bundleNumber": 1,
    "weaponPref": "Spear",
    "secure": 1,
    "goldMultiplier": 1,
    "consolationMultiplier": 0,
    "superEvolve1": "DarkSpear02",
    "cost": 9,
    "visible": 1
  },
  "_build": {
    "scriptVersion": "3-incremental-checkpoint",
    "sourceHash": "7f0de9552765ba7ff9805f340e95c497dc294780b0b6652b57c597f9d2b6b8b1",
    "dependencyHash": "c21234c6d9ef2841ea844e5698b44b5106682728d62fcee191ce4b5875dd713d",
    "generatedAt": 1778014003
  }
}
