{
  "schemaVersion": 3,
  "order": 78,
  "id": "blue-edgy-axe-02",
  "name": "BlueEdgyAxe02",
  "title": "",
  "category": "weapon",
  "rarity": null,
  "stars": 5,
  "evolvedStars": 5,
  "element": null,
  "weaponType": "Axe",
  "stats": {
    "atk": 576,
    "hp": 3020,
    "spd": null,
    "cost": 17
  },
  "image": "https://ik.imagekit.io/r8fsa98s9/weapons/BlueEdgyAxe02.png",
  "refs": {
    "activeSkills": [],
    "passives": [
      "AttackUp5TargetHighTU"
    ],
    "activeSkillsAI": {},
    "aiSequence": null,
    "leaderBuff": null,
    "leaderBuffCondition": null,
    "summonableMonsters": null
  },
  "resolved": {
    "activeSkills": {},
    "passives": {
      "AttackUp5TargetHighTU": {
        "id": "AttackUp5TargetHighTU",
        "found": true,
        "localization": {
          "name": "Attack Up",
          "description": "20% bonus to attacks against units that have a current TU of 150 or more."
        }
      }
    },
    "activeSkillsAI": {},
    "aiSequence": null,
    "leaderCondition": null
  },
  "effect": null,
  "profile": null,
  "internal": {
    "sourceId": "BlueEdgyAxe02",
    "family": "BlueEdgyAxe",
    "source": "apk_extract",
    "treatAsDuplicateOf": null
  },
  "raw": {
    "name": "BlueEdgyAxe02",
    "family": "BlueEdgyAxe",
    "class": "Weapon",
    "passives": {
      "0": "AttackUp5TargetHighTU"
    },
    "stars": 5,
    "evolvedStars": 5,
    "baseAttack": 576,
    "baseMaxHp": 3020,
    "bundleNumber": 1,
    "weaponPref": "Axe",
    "secure": 1,
    "goldMultiplier": 1,
    "consolationMultiplier": 0,
    "evolveFrom": "BlueEdgyAxe01",
    "cost": 17,
    "visible": 1
  },
  "_build": {
    "scriptVersion": "4-passive-localization",
    "sourceHash": "2e668548cbd257613f418ace01fd5cbd0ad877d5198e81f602863ee62cf21ea1",
    "dependencyHash": "3c90aee0b0b2577db63e38f968139a199b2f69ccfe9ee3420ada117531f7c0bf",
    "generatedAt": 1778081744
  }
}
