{
  "schemaVersion": 3,
  "order": 237,
  "id": "bone-blade-sword-03",
  "name": "BoneBladeSword03",
  "category": "weapon",
  "rarity": null,
  "stars": 6,
  "evolvedStars": 6,
  "element": null,
  "weaponType": "Sword",
  "stats": {
    "atk": 649,
    "hp": 3755,
    "spd": null,
    "cost": 23
  },
  "image": "https://ik.imagekit.io/r8fsa98s9/weapons/BoneBladeSword03.png",
  "refs": {
    "activeSkills": [],
    "passives": [
      "AttackUp6AllyLowSpirits"
    ],
    "activeSkillsAI": {},
    "aiSequence": null,
    "leaderBuff": null,
    "leaderBuffCondition": null,
    "summonableMonsters": null
  },
  "resolved": {
    "activeSkills": {},
    "passives": {
      "AttackUp6AllyLowSpirits": {
        "id": "AttackUp6AllyLowSpirits",
        "found": false
      }
    },
    "activeSkillsAI": {},
    "aiSequence": null,
    "leaderCondition": null
  },
  "effect": null,
  "profile": null,
  "internal": {
    "sourceId": "BoneBladeSword03",
    "family": "BoneBladeSword",
    "source": "apk_extract",
    "treatAsDuplicateOf": null
  },
  "raw": {
    "name": "BoneBladeSword03",
    "family": "BoneBladeSword",
    "class": "Weapon",
    "passives": {
      "0": "AttackUp6AllyLowSpirits"
    },
    "stars": 6,
    "evolvedStars": 6,
    "baseAttack": 649,
    "baseMaxHp": 3755,
    "bundleNumber": 1,
    "weaponPref": "Sword",
    "secure": 1,
    "goldMultiplier": 1,
    "consolationMultiplier": 0,
    "evolveFrom": "BoneBladeSword02",
    "cost": 23,
    "visible": 1
  },
  "_build": {
    "scriptVersion": "3-incremental-checkpoint",
    "sourceHash": "88da3f7b75437c1c3117f17f2908d849ae1a2819114a2fded783d75be2aaad79",
    "dependencyHash": "78f0d82ce1631515cdd6f036424a536d07655ed22f6799488009aeba5b843c98",
    "generatedAt": 1778014009
  }
}
