{
  "schemaVersion": 3,
  "order": 359,
  "id": "velantha",
  "sourceId": "GreenThornSpear01",
  "name": "Velantha",
  "title": "",
  "secondName": "",
  "description": "A goddess guards the forests of the elves. None know her name, for it can only be spoken in the ancient tongue, but the name of her spear survives. Velantha: the sunlight which pierces even the thickest canopy.",
  "category": "weapon",
  "rarity": null,
  "stars": 4,
  "evolvedStars": 5,
  "element": null,
  "weaponType": "Spear",
  "stats": {
    "atk": 415,
    "hp": 2900,
    "spd": null,
    "cost": 11
  },
  "hp": 2900,
  "atk": 415,
  "spd": null,
  "cost": 11,
  "image": "https://ik.imagekit.io/r8fsa98s9/weapons/GreenThornSpear01.png",
  "imageVariants": [],
  "forms": [],
  "activeSkills": [],
  "passiveSkills": [
    "HasteUp4Survivor250TU"
  ],
  "leaderSkills": [],
  "refs": {
    "activeSkills": [],
    "passives": [
      "HasteUp4Survivor250TU"
    ],
    "activeSkillsAI": {},
    "aiSequence": null,
    "leaderBuff": null,
    "leaderBuffCondition": null,
    "summonableMonsters": null
  },
  "resolved": {
    "activeSkills": {},
    "passives": {
      "HasteUp4Survivor250TU": {
        "id": "HasteUp4Survivor250TU",
        "found": true,
        "localization": {
          "name": "TU Cost Down",
          "description": "10% reduction to TU costs if the equipped unit has survived for 250TU on the battlefield."
        }
      }
    },
    "activeSkillsAI": {},
    "aiSequence": null,
    "leaderCondition": null
  },
  "effect": null,
  "profile": null,
  "internal": {
    "sourceId": "GreenThornSpear01",
    "family": "GreenThornSpear",
    "source": "apk_extract",
    "treatAsDuplicateOf": null
  },
  "raw": {
    "name": "GreenThornSpear01",
    "family": "GreenThornSpear",
    "class": "Weapon",
    "passives": {
      "0": "HasteUp4Survivor250TU"
    },
    "stars": 4,
    "evolvedStars": 5,
    "baseAttack": 415,
    "baseMaxHp": 2900,
    "bundleNumber": 6,
    "weaponPref": "Spear",
    "secure": 1,
    "goldMultiplier": 1,
    "consolationMultiplier": 0,
    "superEvolve1": "GreenThornSpear02",
    "cost": 11,
    "visible": 1
  },
  "_build": {
    "scriptVersion": "6-character-family-states",
    "sourceHash": "1b6b3411adc5256950c6566898cfd2ce600222a076db8195bc961cc7979f6573",
    "dependencyHash": "3ffb1cfce0190dd3e46134e65337254993185e70f962fdbffdadce66b78cff18",
    "generatedAt": 1782488846
  }
}
