{
  "schemaVersion": 3,
  "order": 468,
  "id": "axe-of-baihu",
  "sourceId": "WhiteTigerGreatAxe01",
  "name": "Axe of Baihu",
  "title": "",
  "secondName": "",
  "description": "An axe holding the power of the White Tiger—the guardian beast of the West. Its fang-like blade, hard enough to crush even diamonds, shines beautifully yet coldly, just like the stars.",
  "category": "weapon",
  "rarity": null,
  "stars": 4,
  "evolvedStars": 6,
  "element": null,
  "weaponType": "GreatAxe",
  "stats": {
    "atk": 527,
    "hp": 2740,
    "spd": null,
    "cost": 11
  },
  "hp": 2740,
  "atk": 527,
  "spd": null,
  "cost": 11,
  "image": "https://ik.imagekit.io/r8fsa98s9/weapons/WhiteTigerGreatAxe01.png",
  "imageVariants": [],
  "forms": [],
  "activeSkills": [],
  "passiveSkills": [
    "AttackUp4TargetRevenge"
  ],
  "leaderSkills": [],
  "refs": {
    "activeSkills": [],
    "passives": [
      "AttackUp4TargetRevenge"
    ],
    "activeSkillsAI": {},
    "aiSequence": null,
    "leaderBuff": null,
    "leaderBuffCondition": null,
    "summonableMonsters": null
  },
  "resolved": {
    "activeSkills": {},
    "passives": {
      "AttackUp4TargetRevenge": {
        "id": "AttackUp4TargetRevenge",
        "found": true,
        "localization": {
          "name": "Attack Up",
          "description": "15% bonus to attacks against units with a Revenge passive skill."
        }
      }
    },
    "activeSkillsAI": {},
    "aiSequence": null,
    "leaderCondition": null
  },
  "effect": null,
  "profile": null,
  "internal": {
    "sourceId": "WhiteTigerGreatAxe01",
    "family": "WhiteTigerGreatAxe",
    "source": "apk_extract",
    "treatAsDuplicateOf": null
  },
  "raw": {
    "name": "WhiteTigerGreatAxe01",
    "family": "WhiteTigerGreatAxe",
    "class": "Weapon",
    "passives": {
      "0": "AttackUp4TargetRevenge"
    },
    "stars": 4,
    "evolvedStars": 6,
    "baseAttack": 527,
    "baseMaxHp": 2740,
    "bundleNumber": 8,
    "weaponPref": "GreatAxe",
    "secure": 1,
    "goldMultiplier": 1,
    "consolationMultiplier": 0,
    "superEvolve1": "WhiteTigerGreatAxe02",
    "cost": 11,
    "visible": 1
  },
  "_build": {
    "scriptVersion": "6-character-family-states",
    "sourceHash": "2140f7425070643797c2605d283f3221a6d5e6ef0f38224d52cfefe5480a05a4",
    "dependencyHash": "8f563974d049593ff1a18c971e6ba2fff56543e586cbbeae1b2918931943ab8d",
    "generatedAt": 1782487521
  }
}
