{
  "schemaVersion": 3,
  "order": 498,
  "id": "arondight",
  "sourceId": "RoundTableSword01",
  "name": "Arondight",
  "title": "",
  "secondName": "",
  "description": "Twin swords wielded by the current Lancelot. Originally a single blade, Arondight was split into two when its first master betrayed his comrades; one half bears his crime, the other—his punishment.",
  "category": "weapon",
  "rarity": null,
  "stars": 4,
  "evolvedStars": 6,
  "element": null,
  "weaponType": "Sword",
  "stats": {
    "atk": 484,
    "hp": 2955,
    "spd": null,
    "cost": 11
  },
  "hp": 2955,
  "atk": 484,
  "spd": null,
  "cost": 11,
  "image": "https://ik.imagekit.io/r8fsa98s9/weapons/RoundTableSword01.png",
  "imageVariants": [],
  "forms": [],
  "activeSkills": [],
  "passiveSkills": [
    "AttackUp4StealthAllies"
  ],
  "leaderSkills": [],
  "refs": {
    "activeSkills": [],
    "passives": [
      "AttackUp4StealthAllies"
    ],
    "activeSkillsAI": {},
    "aiSequence": null,
    "leaderBuff": null,
    "leaderBuffCondition": null,
    "summonableMonsters": null
  },
  "resolved": {
    "activeSkills": {},
    "passives": {
      "AttackUp4StealthAllies": {
        "id": "AttackUp4StealthAllies",
        "found": true,
        "localization": {
          "name": "Attack Up",
          "description": "15% bonus to attacks if 2 or more allies have Stealth."
        }
      }
    },
    "activeSkillsAI": {},
    "aiSequence": null,
    "leaderCondition": null
  },
  "effect": null,
  "profile": null,
  "internal": {
    "sourceId": "RoundTableSword01",
    "family": "RoundTableSword",
    "source": "apk_extract",
    "treatAsDuplicateOf": null
  },
  "raw": {
    "name": "RoundTableSword01",
    "family": "RoundTableSword",
    "class": "Weapon",
    "passives": {
      "0": "AttackUp4StealthAllies"
    },
    "stars": 4,
    "evolvedStars": 6,
    "baseAttack": 484,
    "baseMaxHp": 2955,
    "bundleNumber": 8,
    "weaponPref": "Sword",
    "secure": 1,
    "goldMultiplier": 1,
    "consolationMultiplier": 0,
    "superEvolve1": "RoundTableSword02",
    "cost": 11,
    "visible": 1
  },
  "_build": {
    "scriptVersion": "6-character-family-states",
    "sourceHash": "70e98cf84751f9773ad70a13b2e1f8421c7ea669693e2014d584f81f0013b8bb",
    "dependencyHash": "14769b30b38c218fc6317f35689565e6a9d6a9a22b06e089171072c3f0debc96",
    "generatedAt": 1782493081
  }
}
