{
  "schemaVersion": 3,
  "order": 501,
  "id": "tyrfing",
  "sourceId": "TyrfingSword01",
  "name": "Tyrfing",
  "title": "",
  "secondName": "",
  "description": "A sword that knows no substance too hard to cut, never rusts, and never fails to bring death to its target—but that is not its true nature.\nOnce this cursed blade is drawn, it cares not for its wielder's intentions, and will not be put down until it has made a kill.",
  "category": "weapon",
  "rarity": null,
  "stars": 4,
  "evolvedStars": 6,
  "element": null,
  "weaponType": "Sword",
  "stats": {
    "atk": 471,
    "hp": 3020,
    "spd": null,
    "cost": 11
  },
  "hp": 3020,
  "atk": 471,
  "spd": null,
  "cost": 11,
  "image": "https://ik.imagekit.io/r8fsa98s9/weapons/TyrfingSword01.png",
  "imageVariants": [],
  "forms": [],
  "activeSkills": [],
  "passiveSkills": [
    "AttackUp4NotProtected"
  ],
  "leaderSkills": [],
  "refs": {
    "activeSkills": [],
    "passives": [
      "AttackUp4NotProtected"
    ],
    "activeSkillsAI": {},
    "aiSequence": null,
    "leaderBuff": null,
    "leaderBuffCondition": null,
    "summonableMonsters": null
  },
  "resolved": {
    "activeSkills": {},
    "passives": {
      "AttackUp4NotProtected": {
        "id": "AttackUp4NotProtected",
        "found": true,
        "localization": {
          "name": "Attack Up",
          "description": "15% bonus to attacks if there is no Guardian among allies."
        }
      }
    },
    "activeSkillsAI": {},
    "aiSequence": null,
    "leaderCondition": null
  },
  "effect": null,
  "profile": null,
  "internal": {
    "sourceId": "TyrfingSword01",
    "family": "TyrfingSword",
    "source": "apk_extract",
    "treatAsDuplicateOf": null
  },
  "raw": {
    "name": "TyrfingSword01",
    "family": "TyrfingSword",
    "class": "Weapon",
    "passives": {
      "0": "AttackUp4NotProtected"
    },
    "stars": 4,
    "evolvedStars": 6,
    "baseAttack": 471,
    "baseMaxHp": 3020,
    "bundleNumber": 8,
    "weaponPref": "Sword",
    "secure": 1,
    "goldMultiplier": 1,
    "consolationMultiplier": 0,
    "superEvolve1": "TyrfingSword02",
    "cost": 11,
    "visible": 1
  },
  "_build": {
    "scriptVersion": "6-character-family-states",
    "sourceHash": "81e3b3a1a50e8e33847a9aee76d2b6fa4062c934fc14620505128acffbff3ea2",
    "dependencyHash": "ca6c0da85bdaa5282a5d05f29341011944b526524d9982312b1a5641d5046458",
    "generatedAt": 1782485575
  }
}
