{
  "schemaVersion": 3,
  "order": 621,
  "id": "aetherwing",
  "name": "Aetherwing",
  "title": "",
  "category": "weapon",
  "rarity": null,
  "stars": 4,
  "evolvedStars": 6,
  "element": null,
  "weaponType": "Axe",
  "stats": {
    "atk": 520,
    "hp": 2775,
    "spd": null,
    "cost": 11
  },
  "image": "https://ik.imagekit.io/r8fsa98s9/weapons/ArthurWingAxe01.png",
  "refs": {
    "activeSkills": [],
    "passives": [
      "AttackUp4TargetProtector"
    ],
    "activeSkillsAI": {},
    "aiSequence": null,
    "leaderBuff": null,
    "leaderBuffCondition": null,
    "summonableMonsters": null
  },
  "resolved": {
    "activeSkills": {},
    "passives": {
      "AttackUp4TargetProtector": {
        "id": "AttackUp4TargetProtector",
        "found": true,
        "localization": {
          "name": "Attack Up",
          "description": "15% bonus to attacks against units that are Guardians."
        }
      }
    },
    "activeSkillsAI": {},
    "aiSequence": null,
    "leaderCondition": null
  },
  "effect": null,
  "profile": null,
  "internal": {
    "sourceId": "ArthurWingAxe01",
    "family": "ArthurWingAxe",
    "source": "apk_extract",
    "treatAsDuplicateOf": null
  },
  "raw": {
    "name": "ArthurWingAxe01",
    "family": "ArthurWingAxe",
    "class": "Weapon",
    "passives": {
      "0": "AttackUp4TargetProtector"
    },
    "stars": 4,
    "evolvedStars": 6,
    "baseAttack": 520,
    "baseMaxHp": 2775,
    "bundleNumber": 9,
    "weaponPref": "Axe",
    "secure": 1,
    "goldMultiplier": 1,
    "consolationMultiplier": 1,
    "superEvolve1": "ArthurWingAxe02",
    "cost": 11,
    "visible": 1
  },
  "_build": {
    "scriptVersion": "4-passive-localization",
    "sourceHash": "f8b443afa69a497463fcc4d8f4f7457e8eb094700a24965360670320d7f685d8",
    "dependencyHash": "0f6251874629f7963b087f6b6ab32db1850439241f5bae8d87c0412360a9a637",
    "generatedAt": 1778081761
  }
}
