{
  "schemaVersion": 3,
  "order": 740,
  "id": "turquoise-haze-axe-03",
  "sourceId": "TurquoiseHazeAxe03",
  "name": "TurquoiseHazeAxe03",
  "title": "",
  "secondName": "",
  "description": "",
  "category": "weapon",
  "rarity": null,
  "stars": 6,
  "evolvedStars": 6,
  "element": null,
  "weaponType": "Axe",
  "stats": {
    "atk": 672,
    "hp": 3640,
    "spd": null,
    "cost": 23
  },
  "hp": 3640,
  "atk": 672,
  "spd": null,
  "cost": 23,
  "image": "https://ik.imagekit.io/r8fsa98s9/weapons/TurquoiseHazeAxe03.png",
  "imageVariants": [],
  "forms": [],
  "activeSkills": [],
  "passiveSkills": [
    "AttackUp6TargetActuallyBurning"
  ],
  "leaderSkills": [],
  "refs": {
    "activeSkills": [],
    "passives": [
      "AttackUp6TargetActuallyBurning"
    ],
    "activeSkillsAI": {},
    "aiSequence": null,
    "leaderBuff": null,
    "leaderBuffCondition": null,
    "summonableMonsters": null
  },
  "resolved": {
    "activeSkills": {},
    "passives": {
      "AttackUp6TargetActuallyBurning": {
        "id": "AttackUp6TargetActuallyBurning",
        "found": true,
        "localization": {
          "name": "Attack Up",
          "description": "15% bonus to attacks against burning units."
        }
      }
    },
    "activeSkillsAI": {},
    "aiSequence": null,
    "leaderCondition": null
  },
  "effect": null,
  "profile": null,
  "internal": {
    "sourceId": "TurquoiseHazeAxe03",
    "family": "TurquoiseHazeAxe",
    "source": "apk_extract",
    "treatAsDuplicateOf": null
  },
  "raw": {
    "name": "TurquoiseHazeAxe03",
    "family": "TurquoiseHazeAxe",
    "class": "Weapon",
    "passives": {
      "0": "AttackUp6TargetActuallyBurning"
    },
    "stars": 6,
    "evolvedStars": 6,
    "baseAttack": 672,
    "baseMaxHp": 3640,
    "bundleNumber": 9,
    "weaponPref": "Axe",
    "secure": 1,
    "goldMultiplier": 1,
    "consolationMultiplier": 1,
    "evolveFrom": "TurquoiseHazeAxe02",
    "cost": 23,
    "visible": 1
  },
  "_build": {
    "scriptVersion": "6-character-family-states",
    "sourceHash": "9b6a8d4cef837f6d45f24547d86a8ca62cc1a7fefc401ee07616406f82321e1e",
    "dependencyHash": "62aac9f33497740adb3dc82e983805edad97ed39ffc8030b34db2ce882e8019d",
    "generatedAt": 1782487521
  }
}
