{
  "schemaVersion": 2,
  "source": "locked canonical accessories order",
  "generatedAt": 1780718443,
  "category": "accessories",
  "count": 106,
  "order": [
    {
      "order": 1,
      "sourceOrder": 1,
      "fileHandleOrder": 1,
      "key": "Armor01",
      "sourceId": "Armor01",
      "displayName": "Sturdy Mail",
      "file": "entries/0001_Armor01.json",
      "matchedBy": "canonical"
    },
    {
      "order": 2,
      "sourceOrder": 2,
      "fileHandleOrder": 2,
      "key": "Pickaxe01",
      "sourceId": "Pickaxe01",
      "displayName": "Pickaxe",
      "file": "entries/0002_Pickaxe01.json",
      "matchedBy": "canonical"
    },
    {
      "order": 3,
      "sourceOrder": 3,
      "fileHandleOrder": 3,
      "key": "KukuriKnife01",
      "sourceId": "KukuriKnife01",
      "displayName": "Leaf Blade",
      "file": "entries/0003_KukuriKnife01.json",
      "matchedBy": "canonical"
    },
    {
      "order": 4,
      "sourceOrder": 4,
      "fileHandleOrder": 4,
      "key": "CobraRod01",
      "sourceId": "CobraRod01",
      "displayName": "Cobra Rod",
      "file": "entries/0004_CobraRod01.json",
      "matchedBy": "canonical"
    },
    {
      "order": 5,
      "sourceOrder": 5,
      "fileHandleOrder": 5,
      "key": "HawkCoin01",
      "sourceId": "HawkCoin01",
      "displayName": "Hawk Coin",
      "file": "entries/0005_HawkCoin01.json",
      "matchedBy": "canonical"
    },
    {
      "order": 6,
      "sourceOrder": 6,
      "fileHandleOrder": 6,
      "key": "Bracelet01",
      "sourceId": "Bracelet01",
      "displayName": "Gem Bangle",
      "file": "entries/0006_Bracelet01.json",
      "matchedBy": "canonical"
    },
    {
      "order": 7,
      "sourceOrder": 7,
      "fileHandleOrder": 7,
      "key": "Gauntlet01",
      "sourceId": "Gauntlet01",
      "displayName": "Steel Fist",
      "file": "entries/0007_Gauntlet01.json",
      "matchedBy": "canonical"
    },
    {
      "order": 8,
      "sourceOrder": 8,
      "fileHandleOrder": 8,
      "key": "AlchemyFlask01",
      "sourceId": "AlchemyFlask01",
      "displayName": "Vim Flask",
      "file": "entries/0008_AlchemyFlask01.json",
      "matchedBy": "canonical"
    },
    {
      "order": 9,
      "sourceOrder": 9,
      "fileHandleOrder": 9,
      "key": "GreenRing01",
      "sourceId": "GreenRing01",
      "displayName": "Wise Ring",
      "file": "entries/0009_GreenRing01.json",
      "matchedBy": "canonical"
    },
    {
      "order": 10,
      "sourceOrder": 10,
      "fileHandleOrder": 10,
      "key": "Girdle01",
      "sourceId": "Girdle01",
      "displayName": "Stout Belt",
      "file": "entries/0010_Girdle01.json",
      "matchedBy": "canonical"
    },
    {
      "order": 11,
      "sourceOrder": 11,
      "fileHandleOrder": 11,
      "key": "RedRings01",
      "sourceId": "RedRings01",
      "displayName": "Wild Rings",
      "file": "entries/0011_RedRings01.json",
      "matchedBy": "canonical"
    },
    {
      "order": 12,
      "sourceOrder": 12,
      "fileHandleOrder": 12,
      "key": "Bracer01",
      "sourceId": "Bracer01",
      "displayName": "Strong Arm",
      "file": "entries/0012_Bracer01.json",
      "matchedBy": "canonical"
    },
    {
      "order": 13,
      "sourceOrder": 13,
      "fileHandleOrder": 13,
      "key": "Earrings01",
      "sourceId": "Earrings01",
      "displayName": "Lilac Drops",
      "file": "entries/0013_Earrings01.json",
      "matchedBy": "canonical"
    },
    {
      "order": 14,
      "sourceOrder": 14,
      "fileHandleOrder": 14,
      "key": "Feathers01",
      "sourceId": "Feathers01",
      "displayName": "Fancy Pin",
      "file": "entries/0014_Feathers01.json",
      "matchedBy": "canonical"
    },
    {
      "order": 15,
      "sourceOrder": 15,
      "fileHandleOrder": 15,
      "key": "Skirt01",
      "sourceId": "Skirt01",
      "displayName": "Strike Skirt",
      "file": "entries/0015_Skirt01.json",
      "matchedBy": "canonical"
    },
    {
      "order": 16,
      "sourceOrder": 16,
      "fileHandleOrder": 16,
      "key": "LimePotion01",
      "sourceId": "LimePotion01",
      "displayName": "Vigor Vial",
      "file": "entries/0016_LimePotion01.json",
      "matchedBy": "canonical"
    },
    {
      "order": 17,
      "sourceOrder": 17,
      "fileHandleOrder": 17,
      "key": "RedGreenDroplet01",
      "sourceId": "RedGreenDroplet01",
      "displayName": "Pretty Jewel",
      "file": "entries/0017_RedGreenDroplet01.json",
      "matchedBy": "canonical"
    },
    {
      "order": 18,
      "sourceOrder": 18,
      "fileHandleOrder": 18,
      "key": "BronzePickaxe01",
      "sourceId": "BronzePickaxe01",
      "displayName": "Bronze Axe",
      "file": "entries/0018_BronzePickaxe01.json",
      "matchedBy": "canonical"
    },
    {
      "order": 19,
      "sourceOrder": 19,
      "fileHandleOrder": 19,
      "key": "RitualBlade01",
      "sourceId": "RitualBlade01",
      "displayName": "Ritual Knife",
      "file": "entries/0019_RitualBlade01.json",
      "matchedBy": "canonical"
    },
    {
      "order": 20,
      "sourceOrder": 20,
      "fileHandleOrder": 20,
      "key": "Crown01",
      "sourceId": "Crown01",
      "displayName": "Ptaki Circlet",
      "file": "entries/0020_Crown01.json",
      "matchedBy": "canonical"
    },
    {
      "order": 21,
      "sourceOrder": 21,
      "fileHandleOrder": 21,
      "key": "HookKnife01",
      "sourceId": "HookKnife01",
      "displayName": "Hook Knife",
      "file": "entries/0021_HookKnife01.json",
      "matchedBy": "canonical"
    },
    {
      "order": 22,
      "sourceOrder": 22,
      "fileHandleOrder": 22,
      "key": "Cape01",
      "sourceId": "Cape01",
      "displayName": "Ptaki Cape",
      "file": "entries/0022_Cape01.json",
      "matchedBy": "canonical"
    },
    {
      "order": 23,
      "sourceOrder": 23,
      "fileHandleOrder": 23,
      "key": "WingTiara01",
      "sourceId": "WingTiara01",
      "displayName": "Ptaki Diadem",
      "file": "entries/0023_WingTiara01.json",
      "matchedBy": "canonical"
    },
    {
      "order": 24,
      "sourceOrder": 24,
      "fileHandleOrder": 24,
      "key": "EvilLapelPin01",
      "sourceId": "EvilLapelPin01",
      "displayName": "Cursed Pin",
      "file": "entries/0024_EvilLapelPin01.json",
      "matchedBy": "canonical"
    },
    {
      "order": 25,
      "sourceOrder": 25,
      "fileHandleOrder": 25,
      "key": "Luther01SwordAcc01",
      "sourceId": "Luther01SwordAcc01",
      "displayName": "Luther01SwordAcc01",
      "file": "entries/0025_Luther01SwordAcc01.json",
      "matchedBy": "canonical"
    },
    {
      "order": 26,
      "sourceOrder": 26,
      "fileHandleOrder": 26,
      "key": "RedKnightHelm01",
      "sourceId": "RedKnightHelm01",
      "displayName": "Red Knight Helm",
      "file": "entries/0026_RedKnightHelm01.json",
      "matchedBy": "canonical"
    },
    {
      "order": 27,
      "sourceOrder": 27,
      "fileHandleOrder": 27,
      "key": "SziFire01",
      "sourceId": "SziFire01",
      "displayName": "Szi Flame",
      "file": "entries/0027_SziFire01.json",
      "matchedBy": "canonical"
    },
    {
      "order": 28,
      "sourceOrder": 28,
      "fileHandleOrder": 28,
      "key": "DragonRings01",
      "sourceId": "DragonRings01",
      "displayName": "Dragon Rings",
      "file": "entries/0028_DragonRings01.json",
      "matchedBy": "canonical"
    },
    {
      "order": 29,
      "sourceOrder": 29,
      "fileHandleOrder": 29,
      "key": "AliceRabbitDoll01",
      "sourceId": "AliceRabbitDoll01",
      "displayName": "Tavun Rabbit",
      "file": "entries/0029_AliceRabbitDoll01.json",
      "matchedBy": "canonical"
    },
    {
      "order": 30,
      "sourceOrder": 30,
      "fileHandleOrder": 30,
      "key": "LunaNote01",
      "sourceId": "LunaNote01",
      "displayName": "Luna's Notes",
      "file": "entries/0030_LunaNote01.json",
      "matchedBy": "canonical"
    },
    {
      "order": 31,
      "sourceOrder": 31,
      "fileHandleOrder": 31,
      "key": "SakuraArmor01",
      "sourceId": "SakuraArmor01",
      "displayName": "Oumon Yoroi",
      "file": "entries/0031_SakuraArmor01.json",
      "matchedBy": "canonical"
    },
    {
      "order": 32,
      "sourceOrder": 32,
      "fileHandleOrder": 32,
      "key": "LudmillaGauntlet01",
      "sourceId": "LudmillaGauntlet01",
      "displayName": "Ludmilla's Bracer",
      "file": "entries/0032_LudmillaGauntlet01.json",
      "matchedBy": "canonical"
    },
    {
      "order": 33,
      "sourceOrder": 33,
      "fileHandleOrder": 33,
      "key": "MyshaPauldron01",
      "sourceId": "MyshaPauldron01",
      "displayName": "Inheritor's Bangle",
      "file": "entries/0033_MyshaPauldron01.json",
      "matchedBy": "canonical"
    },
    {
      "order": 34,
      "sourceOrder": 34,
      "fileHandleOrder": 34,
      "key": "SwimRing01",
      "sourceId": "SwimRing01",
      "displayName": "Swim Ring",
      "file": "entries/0034_SwimRing01.json",
      "matchedBy": "canonical"
    },
    {
      "order": 35,
      "sourceOrder": 35,
      "fileHandleOrder": 35,
      "key": "Pearl01",
      "sourceId": "Pearl01",
      "displayName": "Moondrop Pearl",
      "file": "entries/0035_Pearl01.json",
      "matchedBy": "canonical"
    },
    {
      "order": 36,
      "sourceOrder": 36,
      "fileHandleOrder": 36,
      "key": "BlackBelt01",
      "sourceId": "BlackBelt01",
      "displayName": "Kuro-Obi",
      "file": "entries/0036_BlackBelt01.json",
      "matchedBy": "canonical"
    },
    {
      "order": 37,
      "sourceOrder": 37,
      "fileHandleOrder": 37,
      "key": "RizetteBelt01",
      "sourceId": "RizetteBelt01",
      "displayName": "Rizette's Pouch",
      "file": "entries/0037_RizetteBelt01.json",
      "matchedBy": "canonical"
    },
    {
      "order": 38,
      "sourceOrder": 38,
      "fileHandleOrder": 38,
      "key": "AstridHairpin01",
      "sourceId": "AstridHairpin01",
      "displayName": "Astrid's Hairpin",
      "file": "entries/0038_AstridHairpin01.json",
      "matchedBy": "canonical"
    },
    {
      "order": 39,
      "sourceOrder": 39,
      "fileHandleOrder": 39,
      "key": "RolotiaClock01",
      "sourceId": "RolotiaClock01",
      "displayName": "Mortal Timepiece",
      "file": "entries/0039_RolotiaClock01.json",
      "matchedBy": "canonical"
    },
    {
      "order": 40,
      "sourceOrder": 40,
      "fileHandleOrder": 40,
      "key": "ValkyrieMedal01",
      "sourceId": "ValkyrieMedal01",
      "displayName": "Valkyrie Crest",
      "file": "entries/0040_ValkyrieMedal01.json",
      "matchedBy": "canonical"
    },
    {
      "order": 41,
      "sourceOrder": 41,
      "fileHandleOrder": 41,
      "key": "LudmillaJacket01",
      "sourceId": "LudmillaJacket01",
      "displayName": "Leather Raiment",
      "file": "entries/0041_LudmillaJacket01.json",
      "matchedBy": "canonical"
    },
    {
      "order": 42,
      "sourceOrder": 42,
      "fileHandleOrder": 42,
      "key": "HymeliaCrown01",
      "sourceId": "HymeliaCrown01",
      "displayName": "Crown of Hymelia",
      "file": "entries/0042_HymeliaCrown01.json",
      "matchedBy": "canonical"
    },
    {
      "order": 43,
      "sourceOrder": 43,
      "fileHandleOrder": 43,
      "key": "DragonShield01",
      "sourceId": "DragonShield01",
      "displayName": "Shield of the Six",
      "file": "entries/0043_DragonShield01.json",
      "matchedBy": "canonical"
    },
    {
      "order": 44,
      "sourceOrder": 44,
      "fileHandleOrder": 44,
      "key": "CrystalBeads01",
      "sourceId": "CrystalBeads01",
      "displayName": "Holy Maiden's Lumiary",
      "file": "entries/0044_CrystalBeads01.json",
      "matchedBy": "canonical"
    },
    {
      "order": 45,
      "sourceOrder": 45,
      "fileHandleOrder": 45,
      "key": "YukiSunHat01",
      "sourceId": "YukiSunHat01",
      "displayName": "Elegant Sun Hat",
      "file": "entries/0045_YukiSunHat01.json",
      "matchedBy": "canonical"
    },
    {
      "order": 46,
      "sourceOrder": 46,
      "fileHandleOrder": 46,
      "key": "RolotiaSwimsuitClock01",
      "sourceId": "RolotiaSwimsuitClock01",
      "displayName": "Tropical Timekeeper",
      "file": "entries/0046_RolotiaSwimsuitClock01.json",
      "matchedBy": "canonical"
    },
    {
      "order": 47,
      "sourceOrder": 47,
      "fileHandleOrder": 47,
      "key": "Endbringer01",
      "sourceId": "Endbringer01",
      "displayName": "Endbringer01",
      "file": "entries/0047_Endbringer01.json",
      "matchedBy": "canonical"
    },
    {
      "order": 48,
      "sourceOrder": 48,
      "fileHandleOrder": 48,
      "key": "DragonfireBottle01",
      "sourceId": "DragonfireBottle01",
      "displayName": "Dragonfire Flask",
      "file": "entries/0048_DragonfireBottle01.json",
      "matchedBy": "canonical"
    },
    {
      "order": 49,
      "sourceOrder": 49,
      "fileHandleOrder": 49,
      "key": "EnchantedRing01",
      "sourceId": "EnchantedRing01",
      "displayName": "Ring of Withering",
      "file": "entries/0049_EnchantedRing01.json",
      "matchedBy": "canonical"
    },
    {
      "order": 50,
      "sourceOrder": 50,
      "fileHandleOrder": 50,
      "key": "OniSchoolbag01",
      "sourceId": "OniSchoolbag01",
      "displayName": "Devilish Schoolbag",
      "file": "entries/0050_OniSchoolbag01.json",
      "matchedBy": "canonical"
    },
    {
      "order": 51,
      "sourceOrder": 51,
      "fileHandleOrder": 51,
      "key": "DragonPlushie01",
      "sourceId": "DragonPlushie01",
      "displayName": "Santa Claws",
      "file": "entries/0051_DragonPlushie01.json",
      "matchedBy": "canonical"
    },
    {
      "order": 52,
      "sourceOrder": 52,
      "fileHandleOrder": 52,
      "key": "IdolMic01",
      "sourceId": "IdolMic01",
      "displayName": "Trusty Microphone",
      "file": "entries/0052_IdolMic01.json",
      "matchedBy": "canonical"
    },
    {
      "order": 53,
      "sourceOrder": 53,
      "fileHandleOrder": 53,
      "key": "GlassSyringe01",
      "sourceId": "GlassSyringe01",
      "displayName": "Booster Shot",
      "file": "entries/0053_GlassSyringe01.json",
      "matchedBy": "canonical"
    },
    {
      "order": 54,
      "sourceOrder": 54,
      "fileHandleOrder": 54,
      "key": "Katashiro01",
      "sourceId": "Katashiro01",
      "displayName": "Sage's Katashiro",
      "file": "entries/0054_Katashiro01.json",
      "matchedBy": "canonical"
    },
    {
      "order": 55,
      "sourceOrder": 55,
      "fileHandleOrder": 55,
      "key": "BlackSnowCrown01",
      "sourceId": "BlackSnowCrown01",
      "displayName": "Ebony Crown",
      "file": "entries/0055_BlackSnowCrown01.json",
      "matchedBy": "canonical"
    },
    {
      "order": 56,
      "sourceOrder": 56,
      "fileHandleOrder": 56,
      "key": "MaidHairBand01",
      "sourceId": "MaidHairBand01",
      "displayName": "Maid's Bonnet",
      "file": "entries/0056_MaidHairBand01.json",
      "matchedBy": "canonical"
    },
    {
      "order": 57,
      "sourceOrder": 57,
      "fileHandleOrder": 57,
      "key": "BunnyHairBand01",
      "sourceId": "BunnyHairBand01",
      "displayName": "Bunny Headband",
      "file": "entries/0057_BunnyHairBand01.json",
      "matchedBy": "canonical"
    },
    {
      "order": 58,
      "sourceOrder": 58,
      "fileHandleOrder": 58,
      "key": "ChampionBelt01",
      "sourceId": "ChampionBelt01",
      "displayName": "Champion's Belt",
      "file": "entries/0058_ChampionBelt01.json",
      "matchedBy": "canonical"
    },
    {
      "order": 59,
      "sourceOrder": 59,
      "fileHandleOrder": 59,
      "key": "CyrusRings01",
      "sourceId": "CyrusRings01",
      "displayName": "The Devil",
      "file": "entries/0059_CyrusRings01.json",
      "matchedBy": "canonical"
    },
    {
      "order": 60,
      "sourceOrder": 60,
      "fileHandleOrder": 60,
      "key": "SquidArmor01",
      "sourceId": "SquidArmor01",
      "displayName": "Found Fathoms",
      "file": "entries/0060_SquidArmor01.json",
      "matchedBy": "canonical"
    },
    {
      "order": 61,
      "sourceOrder": 61,
      "fileHandleOrder": 61,
      "key": "JeanneFlag01",
      "sourceId": "JeanneFlag01",
      "displayName": "Maiden's Banner",
      "file": "entries/0061_JeanneFlag01.json",
      "matchedBy": "canonical"
    },
    {
      "order": 62,
      "sourceOrder": 62,
      "fileHandleOrder": 62,
      "key": "ThunderlingHelmet01",
      "sourceId": "ThunderlingHelmet01",
      "displayName": "Bolt-Bearer Helm",
      "file": "entries/0062_ThunderlingHelmet01.json",
      "matchedBy": "canonical"
    },
    {
      "order": 63,
      "sourceOrder": 63,
      "fileHandleOrder": 63,
      "key": "EternalRing01",
      "sourceId": "EternalRing01",
      "displayName": "Daybreak Band",
      "file": "entries/0063_EternalRing01.json",
      "matchedBy": "canonical"
    },
    {
      "order": 64,
      "sourceOrder": 64,
      "fileHandleOrder": 64,
      "key": "ExeterniaSchematics01",
      "sourceId": "ExeterniaSchematics01",
      "displayName": "Sword Diagram",
      "file": "entries/0064_ExeterniaSchematics01.json",
      "matchedBy": "canonical"
    },
    {
      "order": 65,
      "sourceOrder": 65,
      "fileHandleOrder": 65,
      "key": "DiabolosArmor01",
      "sourceId": "DiabolosArmor01",
      "displayName": "Evershade Armor",
      "file": "entries/0065_DiabolosArmor01.json",
      "matchedBy": "canonical"
    },
    {
      "order": 66,
      "sourceOrder": 66,
      "fileHandleOrder": 66,
      "key": "OrcanixShield01",
      "sourceId": "OrcanixShield01",
      "displayName": "Orcanix's Aegis",
      "file": "entries/0066_OrcanixShield01.json",
      "matchedBy": "canonical"
    },
    {
      "order": 67,
      "sourceOrder": 67,
      "fileHandleOrder": 67,
      "key": "MinotaurHelmet01",
      "sourceId": "MinotaurHelmet01",
      "displayName": "The Select's Helm",
      "file": "entries/0067_MinotaurHelmet01.json",
      "matchedBy": "canonical"
    },
    {
      "order": 68,
      "sourceOrder": 68,
      "fileHandleOrder": 68,
      "key": "TaotieRing01",
      "sourceId": "TaotieRing01",
      "displayName": "Scenic Snowband",
      "file": "entries/0068_TaotieRing01.json",
      "matchedBy": "canonical"
    },
    {
      "order": 69,
      "sourceOrder": 69,
      "fileHandleOrder": 69,
      "key": "BikkiFan01",
      "sourceId": "BikkiFan01",
      "displayName": "Prized Suehiro",
      "file": "entries/0069_BikkiFan01.json",
      "matchedBy": "canonical"
    },
    {
      "order": 70,
      "sourceOrder": 70,
      "fileHandleOrder": 70,
      "key": "ArcaneRing01",
      "sourceId": "ArcaneRing01",
      "displayName": "Everlight Ring",
      "file": "entries/0070_ArcaneRing01.json",
      "matchedBy": "canonical"
    },
    {
      "order": 71,
      "sourceOrder": 71,
      "fileHandleOrder": 71,
      "key": "AirDragonArmor01",
      "sourceId": "AirDragonArmor01",
      "displayName": "OWM-Armor",
      "file": "entries/0071_AirDragonArmor01.json",
      "matchedBy": "canonical"
    },
    {
      "order": 72,
      "sourceOrder": 72,
      "fileHandleOrder": 72,
      "key": "JeanneCrown01",
      "sourceId": "JeanneCrown01",
      "displayName": "Crown of Flowers",
      "file": "entries/0072_JeanneCrown01.json",
      "matchedBy": "canonical"
    },
    {
      "order": 73,
      "sourceOrder": 73,
      "fileHandleOrder": 73,
      "key": "BikkiHelmet01",
      "sourceId": "BikkiHelmet01",
      "displayName": "Prized Aquakabuto",
      "file": "entries/0073_BikkiHelmet01.json",
      "matchedBy": "canonical"
    },
    {
      "order": 74,
      "sourceOrder": 74,
      "fileHandleOrder": 74,
      "key": "OrcanixCloak01",
      "sourceId": "OrcanixCloak01",
      "displayName": "Hel's Almuce",
      "file": "entries/0074_OrcanixCloak01.json",
      "matchedBy": "canonical"
    },
    {
      "order": 75,
      "sourceOrder": 75,
      "fileHandleOrder": 75,
      "key": "KaijuShield01",
      "sourceId": "KaijuShield01",
      "displayName": "Gluttonous Shield",
      "file": "entries/0075_KaijuShield01.json",
      "matchedBy": "canonical"
    },
    {
      "order": 76,
      "sourceOrder": 76,
      "fileHandleOrder": 76,
      "key": "MagnifoDagger01",
      "sourceId": "MagnifoDagger01",
      "displayName": "Heathen Dagger",
      "file": "entries/0076_MagnifoDagger01.json",
      "matchedBy": "canonical"
    },
    {
      "order": 77,
      "sourceOrder": 77,
      "fileHandleOrder": 77,
      "key": "FornaxosArmor01",
      "sourceId": "FornaxosArmor01",
      "displayName": "Inferno Armor",
      "file": "entries/0077_FornaxosArmor01.json",
      "matchedBy": "canonical"
    },
    {
      "order": 78,
      "sourceOrder": 78,
      "fileHandleOrder": 78,
      "key": "KaidarosHelmet01",
      "sourceId": "KaidarosHelmet01",
      "displayName": "Azure Elegy Helm",
      "file": "entries/0078_KaidarosHelmet01.json",
      "matchedBy": "canonical"
    },
    {
      "order": 79,
      "sourceOrder": 79,
      "fileHandleOrder": 79,
      "key": "BahamutShield01",
      "sourceId": "BahamutShield01",
      "displayName": "Scute of Finality",
      "file": "entries/0079_BahamutShield01.json",
      "matchedBy": "canonical"
    },
    {
      "order": 80,
      "sourceOrder": 80,
      "fileHandleOrder": 80,
      "key": "ExeterniaTalisman01",
      "sourceId": "ExeterniaTalisman01",
      "displayName": "Glowing Aegis",
      "file": "entries/0080_ExeterniaTalisman01.json",
      "matchedBy": "canonical"
    },
    {
      "order": 81,
      "sourceOrder": 81,
      "fileHandleOrder": 81,
      "key": "NovaBlastArmor01",
      "sourceId": "NovaBlastArmor01",
      "displayName": "Blueflash Armor",
      "file": "entries/0081_NovaBlastArmor01.json",
      "matchedBy": "canonical"
    },
    {
      "order": 82,
      "sourceOrder": 82,
      "fileHandleOrder": 82,
      "key": "MusashiButterfly01",
      "sourceId": "MusashiButterfly01",
      "displayName": "Butterfly Hairpin",
      "file": "entries/0082_MusashiButterfly01.json",
      "matchedBy": "canonical"
    },
    {
      "order": 83,
      "sourceOrder": 83,
      "fileHandleOrder": 83,
      "key": "ArcaneShield01",
      "sourceId": "ArcaneShield01",
      "displayName": "Will Unto Eternity",
      "file": "entries/0083_ArcaneShield01.json",
      "matchedBy": "canonical"
    },
    {
      "order": 84,
      "sourceOrder": 84,
      "fileHandleOrder": 84,
      "key": "NovaBlastHelmet01",
      "sourceId": "NovaBlastHelmet01",
      "displayName": "Boltblast Helmet",
      "file": "entries/0084_NovaBlastHelmet01.json",
      "matchedBy": "canonical"
    },
    {
      "order": 85,
      "sourceOrder": 85,
      "fileHandleOrder": 85,
      "key": "NapoleonBadge01",
      "sourceId": "NapoleonBadge01",
      "displayName": "Lugrasse's Star",
      "file": "entries/0085_NapoleonBadge01.json",
      "matchedBy": "canonical"
    },
    {
      "order": 86,
      "sourceOrder": 86,
      "fileHandleOrder": 86,
      "key": "Hakama01",
      "sourceId": "Hakama01",
      "displayName": "Pale Blue Haori",
      "file": "entries/0086_Hakama01.json",
      "matchedBy": "canonical"
    },
    {
      "order": 87,
      "sourceOrder": 87,
      "fileHandleOrder": 87,
      "key": "TristanHarp01",
      "sourceId": "TristanHarp01",
      "displayName": "Voice of Woe",
      "file": "entries/0087_TristanHarp01.json",
      "matchedBy": "canonical"
    },
    {
      "order": 88,
      "sourceOrder": 88,
      "fileHandleOrder": 88,
      "key": "KingChessPiece01",
      "sourceId": "KingChessPiece01",
      "displayName": "King of Camelot",
      "file": "entries/0088_KingChessPiece01.json",
      "matchedBy": "canonical"
    },
    {
      "order": 89,
      "sourceOrder": 89,
      "fileHandleOrder": 89,
      "key": "MermaidPearl01",
      "sourceId": "MermaidPearl01",
      "displayName": "Mermaid's Teardrop",
      "file": "entries/0089_MermaidPearl01.json",
      "matchedBy": "canonical"
    },
    {
      "order": 90,
      "sourceOrder": 90,
      "fileHandleOrder": 90,
      "key": "BikkiScroll01",
      "sourceId": "BikkiScroll01",
      "displayName": "Kisen Scroll",
      "file": "entries/0090_BikkiScroll01.json",
      "matchedBy": "canonical"
    },
    {
      "order": 91,
      "sourceOrder": 91,
      "fileHandleOrder": 91,
      "key": "DaVinciNecklace01",
      "sourceId": "DaVinciNecklace01",
      "displayName": "Lovers' Oath",
      "file": "entries/0091_DaVinciNecklace01.json",
      "matchedBy": "canonical"
    },
    {
      "order": 92,
      "sourceOrder": 92,
      "fileHandleOrder": 92,
      "key": "YamatoTurret01",
      "sourceId": "YamatoTurret01",
      "displayName": "Thundering Turret",
      "file": "entries/0092_YamatoTurret01.json",
      "matchedBy": "canonical"
    },
    {
      "order": 93,
      "sourceOrder": 93,
      "fileHandleOrder": 93,
      "key": "ZoroMask01",
      "sourceId": "ZoroMask01",
      "displayName": "Mask of a Thief",
      "file": "entries/0093_ZoroMask01.json",
      "matchedBy": "canonical"
    },
    {
      "order": 94,
      "sourceOrder": 94,
      "fileHandleOrder": 94,
      "key": "ElizabethEarring01",
      "sourceId": "ElizabethEarring01",
      "displayName": "The Royal Sapphire",
      "file": "entries/0094_ElizabethEarring01.json",
      "matchedBy": "canonical"
    },
    {
      "order": 95,
      "sourceOrder": 95,
      "fileHandleOrder": 95,
      "key": "ChronosClock01",
      "sourceId": "ChronosClock01",
      "displayName": "World Clock",
      "file": "entries/0095_ChronosClock01.json",
      "matchedBy": "canonical"
    },
    {
      "order": 96,
      "sourceOrder": 96,
      "fileHandleOrder": 96,
      "key": "SilverKnightArmor01",
      "sourceId": "SilverKnightArmor01",
      "displayName": "Silverlight Armor",
      "file": "entries/0096_SilverKnightArmor01.json",
      "matchedBy": "canonical"
    },
    {
      "order": 97,
      "sourceOrder": 97,
      "fileHandleOrder": 97,
      "key": "SakamotoCloak01",
      "sourceId": "SakamotoCloak01",
      "displayName": "Cloak of Dawn",
      "file": "entries/0097_SakamotoCloak01.json",
      "matchedBy": "canonical"
    },
    {
      "order": 98,
      "sourceOrder": 98,
      "fileHandleOrder": 98,
      "key": "BergarianHelmet01",
      "sourceId": "BergarianHelmet01",
      "displayName": "Apocalypse Hat",
      "file": "entries/0098_BergarianHelmet01.json",
      "matchedBy": "canonical"
    },
    {
      "order": 99,
      "sourceOrder": 99,
      "fileHandleOrder": 99,
      "key": "AnastasiaHat01",
      "sourceId": "AnastasiaHat01",
      "displayName": "Frostlite Kubanka",
      "file": "entries/0099_AnastasiaHat01.json",
      "matchedBy": "canonical"
    },
    {
      "order": 100,
      "sourceOrder": 100,
      "fileHandleOrder": 100,
      "key": "BahamutCollar01",
      "sourceId": "BahamutCollar01",
      "displayName": "The Dragonbinder",
      "file": "entries/0100_BahamutCollar01.json",
      "matchedBy": "canonical"
    },
    {
      "order": 101,
      "sourceOrder": 101,
      "fileHandleOrder": 101,
      "key": "ZeusGauntlet01",
      "sourceId": "ZeusGauntlet01",
      "displayName": "Sturmhond",
      "file": "entries/0101_ZeusGauntlet01.json",
      "matchedBy": "canonical"
    },
    {
      "order": 102,
      "sourceOrder": 102,
      "fileHandleOrder": 102,
      "key": "KenshinBracelet01",
      "sourceId": "KenshinBracelet01",
      "displayName": "Dispelling Beads",
      "file": "entries/0102_KenshinBracelet01.json",
      "matchedBy": "canonical"
    },
    {
      "order": 103,
      "sourceOrder": 103,
      "fileHandleOrder": 103,
      "key": "ThorBelt01",
      "sourceId": "ThorBelt01",
      "displayName": "Morphing Belt",
      "file": "entries/0103_ThorBelt01.json",
      "matchedBy": "canonical"
    },
    {
      "order": 104,
      "sourceOrder": 104,
      "fileHandleOrder": 104,
      "key": "ChopinBaton01",
      "sourceId": "ChopinBaton01",
      "displayName": "Moonlight Baton",
      "file": "entries/0104_ChopinBaton01.json",
      "matchedBy": "canonical"
    },
    {
      "order": 105,
      "sourceOrder": 105,
      "fileHandleOrder": 105,
      "key": "LinkedRings01",
      "sourceId": "LinkedRings01",
      "displayName": "Entwined Forever",
      "file": "entries/0105_LinkedRings01.json",
      "matchedBy": "canonical"
    },
    {
      "order": 106,
      "sourceOrder": 106,
      "fileHandleOrder": 106,
      "key": "VictoriaCrown01",
      "sourceId": "VictoriaCrown01",
      "displayName": "Swan Crown",
      "file": "entries/0106_VictoriaCrown01.json",
      "matchedBy": "canonical"
    }
  ]
}
