{
  "schemaVersion": 1,
  "family": "JeanneAngel",
  "order": 226,
  "name": "Mikaela",
  "title": "",
  "rarity": "SSR",
  "image": "https://ik.imagekit.io/r8fsa98s9/characters/JeanneAngel01.png",
  "states": [
    {
      "state": "base",
      "stars": 5,
      "sourceId": "JeanneAngel01",
      "dataSourceId": "JeanneAngel01",
      "image": "https://ik.imagekit.io/r8fsa98s9/characters/JeanneAngel01.png",
      "name": "Mikaela",
      "title": "",
      "description": "Jeanne's twin sister and guardian angel, revived with holy power to watch over her once again.",
      "hasRawForm": true
    },
    {
      "state": "evolved",
      "stars": 6,
      "sourceId": "JeanneAngel02",
      "dataSourceId": "JeanneAngel02",
      "image": "https://ik.imagekit.io/r8fsa98s9/characters/JeanneAngel02.png",
      "name": "Mikaela",
      "title": "",
      "description": "Jeanne's twin sister and guardian angel, revived with holy power to watch over her once again.",
      "hasRawForm": true
    },
    {
      "state": "final",
      "stars": 6,
      "sourceId": "JeanneAngel03",
      "dataSourceId": "JeanneAngel02",
      "image": "https://ik.imagekit.io/r8fsa98s9/characters/JeanneAngel03.png",
      "name": "Mikaela",
      "title": "",
      "description": "Jeanne's twin sister and guardian angel, revived with holy power to watch over her once again.",
      "hasRawForm": false
    }
  ],
  "rawFormSourceIds": [
    "JeanneAngel01",
    "JeanneAngel02"
  ],
  "_build": {
    "scriptVersion": "6-character-family-states",
    "generatedAt": 1780690138,
    "sourceHash": "e295717473093f406c505e09ed92a284d980339dddb1ad4b49a930ea2830d08c"
  }
}
