{
  "schemaVersion": 3,
  "order": 355,
  "id": "mega-elmina",
  "name": "Mega Elmina",
  "title": "",
  "description": "",
  "category": "bosse",
  "rarity": null,
  "stars": 6,
  "evolvedStars": 6,
  "element": "Light",
  "weaponType": "Hammer",
  "stats": {
    "atk": 4000,
    "hp": 178000,
    "spd": 498,
    "cost": 999
  },
  "image": "https://ik.imagekit.io/r8fsa98s9/characters/ElminaModern03.png",
  "refs": {
    "activeSkills": [
      "DoubleAttackAElminaModernBoss",
      "SuperModeAElminaModernBoss",
      "StrongSingleAttackAElminaModernBoss",
      "PushBackAElminaModernBoss"
    ],
    "passives": [
      "PlanAPassiveAElminaModernBoss",
      "PlanBPassiveAElminaModernBoss"
    ],
    "activeSkillsAI": {},
    "aiSequence": null,
    "leaderBuff": null,
    "leaderBuffCondition": null,
    "summonableMonsters": null
  },
  "resolved": {
    "activeSkills": {
      "DoubleAttackAElminaModernBoss": {
        "id": "DoubleAttackAElminaModernBoss",
        "found": true,
        "localization": {
          "name": "Photon Cut",
          "description": "200% damage to 2 enemies, plus 150% for each Charge stored on the user (max of 650% total damage). This attack ignores any enemy status effects (including Stealth), damage reduction effects, and skin passive skills.",
          "selected": "Up to 650% damage, ignores damage reduction"
        },
        "ability": {
          "name": "DoubleAttackAElminaModernBoss",
          "class": "Ability",
          "abilityScalor": 1,
          "conditionalAbilityScalors": [
            2.5,
            4,
            5.5
          ],
          "config": "DoubleAttackAElminaModernBoss",
          "tuCost": 70,
          "useLimit": 0,
          "spiritGain": 3,
          "blockTargetManipulation": 0,
          "showConfirmation": 0
        },
        "config": {
          "class": "AbilityConfig",
          "targetingData": "2Enemy",
          "components": [
            "Damage",
            "ApplyBuff"
          ],
          "componentOverrides": [
            {
              "applyToTargetType": "Enemy",
              "damageBoosts": [
                "RegularAttackDamageBoost"
              ],
              "damageFlags": [
                "IgnoreArmor",
                "IgnoreSkin",
                "Sneak"
              ]
            },
            {
              "buffs": [
                "StoreEnergy"
              ],
              "showMissConditions": "ShowNoMiss",
              "applyToSourceOnly": true,
              "skipAbilityEffect": true
            }
          ],
          "enemyEventType": "Hit",
          "sourceEventType": "Finish",
          "abilityEffect": "ElminaModernAttack1",
          "flags": [
            "IgnoreStealth"
          ],
          "attackScalors": [
            "GoodIfCharged1",
            "GoodIfCharged2",
            "GoodIfCharged3"
          ],
          "conditionedAbilityEffects": [
            "ElminaModernAttack1",
            "ElminaModernAttack1",
            "ElminaModernAttack1"
          ],
          "recommendEffectWhenUsable": -1
        },
        "targetingData": {
          "class": "TargetingData",
          "enemyTargets": 2
        },
        "abilityEffect": {
          "class": "AbilityEffect",
          "delays": [
            0,
            0.3,
            0.4,
            0,
            0,
            0,
            0,
            0,
            0.2,
            0.4,
            0,
            0.1
          ],
          "prefabs": [
            "batsfx_prefab/batsfx_specialattacksfx1",
            "batfx_ElminaModern/batfx_quickcharge7",
            "batfx_ElminaModern/batfx_smear5",
            "batfx_deadlyvampire1/batfx_camerashake1",
            "batsfx_prefab/batsfx_multislash1",
            "batfx_ElminaModern/batfx_groundimpactMulti1",
            "batsfx_prefab/batsfx_ring2",
            "batfx_roundtableknightDark/batfx_castingSmoke",
            "batfx_ElminaModern/batfx_groundimpactMulti2",
            "batfx_ElminaModern/batfx_slashNoFlipRed1",
            "batfx_ElminaModern/batfx_slashtrailGlich1",
            "batsfx_prefab/batsfx_slash1"
          ],
          "sortOrderOffset": [
            -2,
            -2,
            2,
            2,
            0,
            5,
            5,
            5,
            5,
            2,
            1,
            2
          ],
          "assetBundles": [
            "audiobundle1",
            "BattleEffectsBundle3",
            "BattleEffectsBundle3",
            "BattleEffectsBundle2",
            "audiobundle1",
            "BattleEffectsBundle3",
            "audiobundle1",
            "BattleEffectsBundle2",
            "BattleEffectsBundle3",
            "BattleEffectsBundle3",
            "BattleEffectsBundle3",
            "audiobundle1"
          ],
          "damagePercents": [
            0,
            0,
            0,
            0,
            0,
            0,
            0,
            0,
            0,
            1,
            0,
            0
          ],
          "damageHitReactions": [
            false,
            false,
            false,
            true,
            false,
            false,
            false,
            false,
            false,
            true,
            true,
            false
          ],
          "forceHitReactions": [
            false,
            false,
            false,
            true,
            false,
            false,
            false,
            false,
            false,
            true,
            false,
            false
          ],
          "useEffectFinishedTimeDelay": [
            true,
            true,
            true,
            true,
            true,
            true,
            true,
            true,
            true,
            true,
            true,
            true
          ],
          "isAbilityUserEffect": [
            true,
            true,
            true,
            false,
            true,
            true,
            true,
            true,
            false,
            false,
            false,
            false
          ]
        },
        "components": {
          "Damage": {
            "class": "DamageAbilityComponent"
          },
          "ApplyBuff": {
            "class": "ApplyBuffAbilityComponent"
          }
        },
        "buffs": {
          "StoreEnergy": {
            "class": "Buff",
            "stackLimit": 3,
            "duration": -1,
            "showAsTimer": false,
            "stackName": "StoreEnergy",
            "noIconShownOnBattleStatus": true,
            "usesStackCountDescription": true,
            "iconSpriteName": "IconPinkCharge01"
          }
        },
        "attackScalors": {
          "GoodIfCharged1": {
            "class": "AttackScalor",
            "sourceCondition": "IsCharged1"
          },
          "GoodIfCharged2": {
            "class": "AttackScalor",
            "sourceCondition": "IsCharged2"
          },
          "GoodIfCharged3": {
            "class": "AttackScalor",
            "sourceCondition": "IsCharged3"
          }
        },
        "conditions": {}
      },
      "SuperModeAElminaModernBoss": {
        "id": "SuperModeAElminaModernBoss",
        "found": true,
        "localization": {
          "name": "Elmina Unleashed",
          "description": "The user Unleashes for 100TU. If the user is conjured, the user will unleash for 50TU instead. While Unleashed, this unit heals for 1% of max HP at the end of each turn, cannot fall asleep, and has its Attack increased to 1.5x. This attack increase does not stack with Enrage effects. This skill can only be used once each time this unit is on the battlefield.",
          "selected": "User Unleashes"
        },
        "ability": {
          "name": "SuperModeAElminaModernBoss",
          "class": "Ability",
          "config": "SuperModeAElminaModernBoss",
          "tuCost": 1,
          "useLimit": 0,
          "spiritGain": 2,
          "blockTargetManipulation": 0,
          "showConfirmation": 0
        },
        "config": {
          "class": "AbilityConfig",
          "targetingData": "SelfOnly",
          "components": [
            "ApplyBuff",
            "ApplyBuff",
            "ApplyBuff",
            "ApplyBuff"
          ],
          "componentOverrides": [
            {
              "buffs": [
                "EmptyPlaceholder"
              ],
              "applyToTargetType": "Source"
            },
            {
              "buffs": [
                "100TUSuperModeElminaModernBoss",
                "LockSuperModeAElminaModernBoss"
              ],
              "applyConditions": "IsNotSummoned",
              "showMissConditions": "ShowNoMiss",
              "applyToSourceOnly": true,
              "skipAbilityEffect": true
            },
            {
              "buffs": [
                "50TUSuperModeElminaModernBoss",
                "LockSuperModeAElminaModernBoss"
              ],
              "applyConditions": "IsSummoned",
              "showMissConditions": "ShowNoMiss",
              "applyToSourceOnly": true,
              "skipAbilityEffect": true
            },
            {
              "buffs": [
                "AllAlliesPurifyAndAllOtherAlliesGetTurnEBB",
                "LockActive2ExtraTurnAElminaModernBoss"
              ],
              "applyConditions": "ExtraTurnNotLockedActive2ElminaModern",
              "showMissConditions": "ShowNoMiss",
              "applyToSourceOnly": true,
              "skipAbilityEffect": true
            }
          ],
          "sourceEventType": "Finish",
          "abilityEffect": "ElminaModernPowerUp",
          "useCondition": "NotLockedActive2ElminaModern"
        },
        "targetingData": {
          "class": "TargetingData",
          "selfOnly": true
        },
        "abilityEffect": {
          "class": "AbilityEffect",
          "delays": [
            0.4,
            0,
            0,
            1
          ],
          "prefabs": [
            "batfx_ElminaModern/batfx_FootSquare",
            "batfx_ElminaModern/batfx_FootSquare1",
            "batsfx_prefab/batsfx_charge1",
            "batsfx_prefab/batsfx_computersound1"
          ],
          "sortOrderOffset": [
            -2,
            4,
            5,
            5
          ],
          "assetBundles": [
            "BattleEffectsBundle3",
            "BattleEffectsBundle3",
            "audiobundle1",
            "audiobundle1"
          ],
          "damagePercents": [
            0,
            0,
            0,
            0
          ],
          "damageHitReactions": [
            false,
            false,
            false,
            false
          ],
          "forceHitReactions": [
            false,
            false,
            false,
            false
          ],
          "useEffectFinishedTimeDelay": [
            true,
            true,
            true,
            true
          ],
          "isAbilityUserEffect": [
            true,
            true,
            true,
            true
          ]
        },
        "components": {
          "ApplyBuff": {
            "class": "ApplyBuffAbilityComponent"
          }
        },
        "buffs": {
          "100TUSuperModeElminaModernBoss": {
            "class": "Buff",
            "behaviors": [
              "BuffOnMonsterTurnEnd",
              "Immunity",
              "StatOnly"
            ],
            "behaviorOverrides": [
              {
                "selfBuffs": [
                  "1PercentHealMaxHPBoss"
                ],
                "activeMonsterConditions": "AlwaysTrue"
              },
              {
                "stackNamesToBlock": [
                  "Sleep",
                  "SleepDelayed"
                ]
              },
              {
                "conditions": "NotEnraged",
                "scalorStatBonuses": {
                  "Attack": 0.5
                }
              }
            ],
            "stackName": "100TUSuperModeElminaModernBoss",
            "duration": 100,
            "showAsPermanent": false,
            "showAsTimer": true,
            "tags": [
              "SleepImmune"
            ],
            "statusEffect": "ElminaModernStatusNeon",
            "iconSpriteName": "IconRedSleepInvalidZs01"
          },
          "50TUSuperModeElminaModernBoss": {
            "class": "Buff",
            "behaviors": [
              "BuffOnMonsterTurnEnd",
              "Immunity",
              "StatOnly"
            ],
            "behaviorOverrides": [
              {
                "selfBuffs": [
                  "1PercentHealMaxHPBoss"
                ],
                "activeMonsterConditions": "AlwaysTrue"
              },
              {
                "stackNamesToBlock": [
                  "Sleep",
                  "SleepDelayed"
                ]
              },
              {
                "conditions": "NotEnraged",
                "scalorStatBonuses": {
                  "Attack": 0.5
                }
              }
            ],
            "stackName": "50TUSuperModeElminaModernBoss",
            "duration": 50,
            "showAsPermanent": false,
            "showAsTimer": true,
            "tags": [
              "SleepImmune"
            ],
            "statusEffect": "ElminaModernStatusNeon",
            "iconSpriteName": "IconRedSleepInvalidZs01"
          },
          "AllAlliesPurifyAndAllOtherAlliesGetTurnEBB": {
            "class": "Buff",
            "stackName": "AllAlliesPurifyAndAllOtherAlliesGetTurnEBB",
            "behaviors": [
              "EnterBattleBuff",
              "EnterBattleBuff"
            ],
            "behaviorOverrides": [
              {
                "randomAllyBuffs": [
                  "RemoveBuffs"
                ],
                "numRandomToBuff": 4
              },
              {
                "allAlliesButSelfBuffs": [
                  "GiveTurn",
                  "OnExtraTurn",
                  "JustGivenTurn"
                ]
              }
            ],
            "duration": 0,
            "showAsTimer": false,
            "showAsPermanent": false,
            "isHiddenFromPlayers": true
          },
          "EmptyPlaceholder": {
            "class": "Buff",
            "isHiddenFromPlayers": true,
            "duration": 0,
            "showAsTimer": false,
            "showAsPermanent": false
          },
          "LockActive2ExtraTurnAElminaModernBoss": {
            "class": "Buff",
            "stackName": "LockExtraTurnAElminaModern",
            "showAsTimer": false,
            "showAsPermanent": false,
            "isHiddenFromPlayers": true,
            "duration": -1
          },
          "LockSuperModeAElminaModernBoss": {
            "class": "Buff",
            "stackName": "LockSuperModeAElminaModern",
            "showAsTimer": false,
            "showAsPermanent": false,
            "isHiddenFromPlayers": true,
            "duration": -1
          }
        },
        "attackScalors": {},
        "conditions": {
          "ExtraTurnNotLockedActive2ElminaModern": {
            "class": "MonsterConditions",
            "not": {
              "class": "MonsterConditions",
              "buffStackNames": [
                "LockExtraTurnAElminaModern"
              ]
            }
          },
          "IsNotSummoned": {
            "class": "MonsterConditions",
            "not": {
              "class": "MonsterConditions",
              "summoned": true
            }
          },
          "IsSummoned": {
            "class": "MonsterConditions",
            "summoned": true
          },
          "NotLockedActive2ElminaModern": {
            "class": "MonsterConditions",
            "not": {
              "class": "MonsterConditions",
              "buffStackNames": [
                "LockSuperModeAElminaModern"
              ]
            }
          }
        }
      },
      "StrongSingleAttackAElminaModernBoss": {
        "id": "StrongSingleAttackAElminaModernBoss",
        "found": true,
        "localization": {
          "name": "CODE: DELETE",
          "description": "300% damage to 1 enemy, plus 150% for each Charge stored on the user (max of 750% total damage). This attack ignores enemy damage reduction effects and any effects of non-boss enemies that would prevent the target from being defeated.",
          "selected": "300%+ damage, ignores defeat prevention"
        },
        "ability": {
          "name": "StrongSingleAttackAElminaModernBoss",
          "class": "Ability",
          "abilityScalor": 2,
          "conditionalAbilityScalors": [
            3.5,
            5,
            6.5
          ],
          "config": "StrongSingleAttackAElminaModernBoss",
          "tuCost": 50,
          "useLimit": 0,
          "spiritCost": 2,
          "blockTargetManipulation": 0,
          "showConfirmation": 0
        },
        "config": {
          "class": "AbilityConfig",
          "targetingData": "1Enemy",
          "components": [
            "Damage",
            "ApplyBuff"
          ],
          "componentOverrides": [
            {
              "applyToTargetType": "Enemy",
              "damageBoosts": [
                "RegularAttackDamageBoost"
              ],
              "damageFlags": [
                "IgnoreArmor",
                "HardIgnoreBlockDeath"
              ]
            },
            {
              "buffs": [
                "StoreEnergy"
              ],
              "showMissConditions": "ShowNoMiss",
              "applyToSourceOnly": true,
              "skipAbilityEffect": true
            }
          ],
          "enemyEventType": "Hit",
          "sourceEventType": "Finish",
          "abilityEffect": "batfx_ElminaModernSpecial",
          "attackScalors": [
            "GoodIfCharged1",
            "GoodIfCharged2",
            "GoodIfCharged3"
          ],
          "conditionedAbilityEffects": [
            "batfx_ElminaModernSpecial",
            "batfx_ElminaModernSpecial",
            "batfx_ElminaModernSpecial"
          ],
          "recommendEffectWhenUsable": -1
        },
        "targetingData": {
          "class": "TargetingData",
          "enemyTargets": 1
        },
        "abilityEffect": {
          "class": "AbilityEffect",
          "delays": [
            0,
            0,
            0.1,
            1.2,
            0,
            0,
            0.3,
            0,
            0.3,
            0,
            0.2,
            0,
            0,
            0.8,
            0.1,
            0,
            0,
            0,
            0.1
          ],
          "prefabs": [
            "batsfx_prefab/batsfx_glitchcrest1",
            "batfx_ElminaModern/batfx_FootSquare2",
            "batsfx_prefab/batsfx_purify1",
            "batsfx_prefab/batsfx_slash1",
            "batfx_ElminaModern/batfx_slashtrailGlich1",
            "batfx_ElminaModern/batfx_GoemonSlash1",
            "batfx_ElminaModern/batfx_slashtrailGlich1",
            "batsfx_prefab/batsfx_slash1",
            "batfx_ElminaModern/batfx_slashtrailGlich1",
            "batsfx_prefab/batsfx_slash1",
            "batfx_berserkstun1/batfx_berserkstun1",
            "batfx_ElminaModern/batfx_timestrikeantares3",
            "batsfx_prefab/batsfx_computersound1",
            "batfx_rizetteyoungimpact1/batfx_rizetteyoungimpact1",
            "batfx_ElminaModern/batfx_slashtrailGlich1",
            "batsfx_prefab/batsfx_bomb1",
            "batfx_ElminaModern/batfx_Glich4",
            "batsfx_prefab/batsfx_noise",
            "batfx_ElminaModern/batfx_slashtrailGlich1"
          ],
          "sortOrderOffset": [
            10,
            1,
            0,
            0,
            1,
            2,
            1,
            0,
            1,
            0,
            50,
            -2,
            0,
            50,
            1,
            10,
            1,
            10,
            1
          ],
          "assetBundles": [
            "audiobundle1",
            "BattleEffectsBundle3",
            "audiobundle1",
            "audiobundle1",
            "BattleEffectsBundle3",
            "BattleEffectsBundle3",
            "BattleEffectsBundle3",
            "audiobundle1",
            "BattleEffectsBundle3",
            "audiobundle1",
            "BattleEffectsBundle1",
            "BattleEffectsBundle3",
            "audiobundle1",
            "BattleEffectsBundle1",
            "BattleEffectsBundle3",
            "audiobundle1",
            "BattleEffectsBundle3",
            "audiobundle1",
            "BattleEffectsBundle3"
          ],
          "damagePercents": [
            0,
            0,
            0,
            0,
            0,
            0,
            0,
            0,
            0,
            0,
            0,
            0,
            0,
            0,
            1,
            0,
            0,
            0,
            0
          ],
          "damageHitReactions": [
            false,
            false,
            false,
            false,
            false,
            false,
            false,
            false,
            false,
            false,
            false,
            false,
            false,
            false,
            false,
            false,
            false,
            false,
            false
          ],
          "forceHitReactions": [
            false,
            false,
            false,
            false,
            true,
            false,
            true,
            false,
            true,
            false,
            false,
            false,
            false,
            false,
            true,
            false,
            true,
            false,
            true
          ],
          "useEffectFinishedTimeDelay": [
            true,
            true,
            true,
            true,
            true,
            true,
            true,
            true,
            true,
            true,
            true,
            true,
            true,
            true,
            true,
            true,
            true,
            true,
            true
          ],
          "isAbilityUserEffect": [
            true,
            true,
            true,
            true,
            false,
            false,
            false,
            true,
            false,
            true,
            false,
            false,
            true,
            false,
            false,
            true,
            false,
            true,
            false
          ]
        },
        "components": {
          "Damage": {
            "class": "DamageAbilityComponent"
          },
          "ApplyBuff": {
            "class": "ApplyBuffAbilityComponent"
          }
        },
        "buffs": {
          "StoreEnergy": {
            "class": "Buff",
            "stackLimit": 3,
            "duration": -1,
            "showAsTimer": false,
            "stackName": "StoreEnergy",
            "noIconShownOnBattleStatus": true,
            "usesStackCountDescription": true,
            "iconSpriteName": "IconPinkCharge01"
          }
        },
        "attackScalors": {
          "GoodIfCharged1": {
            "class": "AttackScalor",
            "sourceCondition": "IsCharged1"
          },
          "GoodIfCharged2": {
            "class": "AttackScalor",
            "sourceCondition": "IsCharged2"
          },
          "GoodIfCharged3": {
            "class": "AttackScalor",
            "sourceCondition": "IsCharged3"
          }
        },
        "conditions": {}
      },
      "PushBackAElminaModernBoss": {
        "id": "PushBackAElminaModernBoss",
        "found": true,
        "localization": {
          "name": "Phase Out",
          "description": "Exchanges 1 random enemy with an Imposter. The exchanged enemy will be sent to the front of the enemy reinforcements. This exchange will fail if the target is Immovable or if there are less than 4 enemies on the battlefield (no imposter will be added).\n\nThen pulls the user away from the battlefield to the front of your reinforcements. If there are no ally reinforcements, adds enough Elmina's (max 3) to the ally team to still pull the user away to reinforcements.\n\nUsable if the user has defeated 1+ units with attacks while on the battlefield, and there are 2 non-conjured allies on the battlefield.",
          "selected": "User steps back, may exchange enemy with imposter"
        },
        "ability": {
          "name": "PushBackAElminaModernBoss",
          "class": "Ability",
          "config": "PushBackAElminaModernBoss",
          "tuCost": 0,
          "useLimit": 0,
          "spiritCost": 1,
          "blockTargetManipulation": 0,
          "showConfirmation": 0
        },
        "config": {
          "class": "AbilityConfig",
          "targetingData": "RandomEnemy",
          "components": [
            "ApplyBuff",
            "ApplyBuff",
            "ApplyBuff",
            "ApplyBuff",
            "ApplyBuff",
            "ApplyBuff",
            "ApplyBuff"
          ],
          "componentOverrides": [
            {
              "buffs": [
                "EmptyPlaceholder"
              ],
              "applyToTargetType": "Enemy"
            },
            {
              "buffs": [
                "AddImposterNext",
                "SendToFrontOfReinforcements",
                "RemoveBuffs"
              ],
              "applyConditions": "AtLeast4AlliesLeftNotKnockbackImmune",
              "applyToTargetType": "Enemy",
              "skipAbilityEffect": true
            },
            {
              "buffs": [
                "SendToFrontOfReinforcements",
                "RemoveBuffs"
              ],
              "applyConditions": "AllyHasReinforcements",
              "applyToSourceOnly": true,
              "skipAbilityEffect": true,
              "showMissConditions": "ShowNoMiss"
            },
            {
              "buffs": [
                "Add3BossElminaModernCloneToFront"
              ],
              "applyConditions": "2AlliesLeftNot3",
              "showMissConditions": "ShowNoMiss",
              "applyToSourceOnly": true,
              "skipAbilityEffect": true
            },
            {
              "buffs": [
                "Add2BossElminaModernCloneToFront"
              ],
              "applyConditions": "3AlliesLeftNot4",
              "showMissConditions": "ShowNoMiss",
              "applyToSourceOnly": true,
              "skipAbilityEffect": true
            },
            {
              "buffs": [
                "Add1BossElminaModernCloneToFront"
              ],
              "applyConditions": "4AlliesLeftNoReinforcements",
              "showMissConditions": "ShowNoMiss",
              "applyToSourceOnly": true,
              "skipAbilityEffect": true
            },
            {
              "buffs": [
                "SendToBackOfReinforcements",
                "RemoveBuffsIfNotKnockbackImmune"
              ],
              "showMissConditions": "ShowNoMiss",
              "applyToSourceOnly": true,
              "skipAbilityEffect": true
            }
          ],
          "enemyEventType": "Hit",
          "sourceEventType": "Finish",
          "abilityEffect": "batfx_ElminaModernGlich",
          "flags": [
            "Summon",
            "NoDamage",
            "AddBadFriend"
          ],
          "useCondition": "IsKills1AndAtLeast2NonSummonedAllies"
        },
        "targetingData": {
          "class": "TargetingData",
          "randomEnemy": true
        },
        "abilityEffect": {
          "class": "AbilityEffect",
          "delays": [
            0,
            0,
            0,
            1,
            0,
            0.1,
            0,
            1,
            0,
            0,
            0,
            1
          ],
          "prefabs": [
            "batsfx_prefab/batsfx_charge1",
            "batfx_ElminaModern/batfx_timestrikeantares2",
            "batfx_ElminaModern/batfx_Glich2",
            "batsfx_prefab/batsfx_buff1",
            "batsfx_prefab/batsfx_glitchcrest1",
            "batfx_ElminaModern/batfx_cloneGlich",
            "batfx_ElminaModern/batfx_Glich1",
            "batfx_ElminaModern/batfx_Glich1",
            "batfx_ElminaModern/batfx_Glich3",
            "batfx_ElminaModern/batfx_Glich1",
            "batsfx_prefab/batsfx_noise",
            "batsfx_prefab/batsfx_glitchcrest1"
          ],
          "sortOrderOffset": [
            0,
            -2,
            10,
            10,
            10,
            10,
            10,
            10,
            10,
            10,
            10,
            10
          ],
          "assetBundles": [
            "audiobundle1",
            "BattleEffectsBundle3",
            "BattleEffectsBundle3",
            "audiobundle1",
            "audiobundle1",
            "BattleEffectsBundle3",
            "BattleEffectsBundle3",
            "BattleEffectsBundle3",
            "BattleEffectsBundle3",
            "BattleEffectsBundle3",
            "audiobundle1",
            "audiobundle1"
          ],
          "damagePercents": [
            0,
            0,
            0,
            0,
            0,
            0,
            0,
            0,
            0,
            0,
            0,
            0
          ],
          "damageHitReactions": [
            false,
            false,
            false,
            false,
            false,
            false,
            false,
            false,
            false,
            false,
            false,
            false
          ],
          "forceHitReactions": [
            false,
            false,
            false,
            false,
            false,
            false,
            false,
            false,
            false,
            false,
            false,
            false
          ],
          "useEffectFinishedTimeDelay": [
            true,
            true,
            true,
            true,
            true,
            true,
            true,
            true,
            true,
            true,
            true,
            true
          ],
          "isAbilityUserEffect": [
            true,
            true,
            true,
            true,
            true,
            true,
            true,
            false,
            false,
            true,
            true,
            true
          ]
        },
        "components": {
          "ApplyBuff": {
            "class": "ApplyBuffAbilityComponent"
          }
        },
        "buffs": {
          "Add1BossElminaModernCloneToFront": {
            "class": "Buff",
            "behaviors": [
              "SummonMonster"
            ],
            "behaviorOverrides": [
              {
                "cloneSource": true,
                "cloneSourceStats": true,
                "cloneSourceWeapon": true,
                "cloneSourceEquipment": true,
                "frontOfLineup": true
              }
            ],
            "duration": 0,
            "showAsTimer": false,
            "isHiddenFromPlayers": true
          },
          "Add2BossElminaModernCloneToFront": {
            "class": "Buff",
            "behaviors": [
              "SummonMonster",
              "SummonMonster"
            ],
            "behaviorOverrides": [
              {
                "cloneSource": true,
                "cloneSourceStats": true,
                "cloneSourceWeapon": true,
                "cloneSourceEquipment": true,
                "frontOfLineup": true
              },
              {
                "cloneSource": true,
                "cloneSourceStats": true,
                "cloneSourceWeapon": true,
                "cloneSourceEquipment": true,
                "frontOfLineup": true
              }
            ],
            "duration": 0,
            "showAsTimer": false,
            "isHiddenFromPlayers": true
          },
          "Add3BossElminaModernCloneToFront": {
            "class": "Buff",
            "behaviors": [
              "SummonMonster",
              "SummonMonster",
              "SummonMonster"
            ],
            "behaviorOverrides": [
              {
                "cloneSource": true,
                "cloneSourceStats": true,
                "cloneSourceWeapon": true,
                "cloneSourceEquipment": true,
                "frontOfLineup": true
              },
              {
                "cloneSource": true,
                "cloneSourceStats": true,
                "cloneSourceWeapon": true,
                "cloneSourceEquipment": true,
                "frontOfLineup": true
              },
              {
                "cloneSource": true,
                "cloneSourceStats": true,
                "cloneSourceWeapon": true,
                "cloneSourceEquipment": true,
                "frontOfLineup": true
              }
            ],
            "duration": 0,
            "showAsTimer": false,
            "isHiddenFromPlayers": true
          },
          "AddImposterNext": {
            "class": "Buff",
            "behaviors": [
              "SummonMonster"
            ],
            "behaviorOverrides": [
              {
                "monsterType": "Imposter01",
                "frontOfLineup": true
              }
            ],
            "duration": 0,
            "showAsTimer": false,
            "isHiddenFromPlayers": true
          },
          "EmptyPlaceholder": {
            "class": "Buff",
            "isHiddenFromPlayers": true,
            "duration": 0,
            "showAsTimer": false,
            "showAsPermanent": false
          },
          "RemoveBuffs": {
            "class": "Buff",
            "behaviors": [
              "RemoveBuffs"
            ],
            "duration": 0,
            "showAsTimer": false,
            "isHiddenFromPlayers": true
          },
          "RemoveBuffsIfNotKnockbackImmune": {
            "class": "Buff",
            "behaviors": [
              "RemoveBuffs"
            ],
            "duration": 0,
            "showAsTimer": false,
            "isHiddenFromPlayers": true,
            "applyConditions": "NotKnockbackImmune"
          },
          "SendToBackOfReinforcements": {
            "class": "Buff",
            "stackName": "Knockback",
            "behaviors": [
              "SendToReinforcements"
            ],
            "duration": 0,
            "showAsTimer": false,
            "isHiddenFromPlayers": true
          },
          "SendToFrontOfReinforcements": {
            "class": "Buff",
            "stackName": "Pushback",
            "behaviors": [
              "SendToReinforcements"
            ],
            "behaviorOverrides": [
              {
                "frontOfLineup": true
              }
            ],
            "duration": 0,
            "showAsTimer": false,
            "isHiddenFromPlayers": true
          }
        },
        "attackScalors": {},
        "conditions": {
          "2AlliesLeftNot3": {
            "class": "MonsterConditions",
            "allyTeamSize": 2,
            "not": {
              "class": "MonsterConditions",
              "allyTeamSize": 3
            }
          },
          "3AlliesLeftNot4": {
            "class": "MonsterConditions",
            "allyTeamSize": 3,
            "not": {
              "class": "MonsterConditions",
              "allyTeamSize": 4
            }
          },
          "4AlliesLeftNoReinforcements": {
            "class": "MonsterConditions",
            "allyTeamSize": 4,
            "not": {
              "class": "MonsterConditions",
              "allyReinforcements": 1
            }
          },
          "AllyHasReinforcements": {
            "class": "MonsterConditions",
            "allyReinforcements": 1
          },
          "AtLeast4AlliesLeftNotKnockbackImmune": {
            "class": "MonsterConditions",
            "allyTeamSize": 4,
            "not": {
              "class": "MonsterConditions",
              "monsterTags": [
                "KnockbackImmune"
              ]
            }
          },
          "IsKills1AndAtLeast2NonSummonedAllies": {
            "class": "MonsterConditions",
            "killsMade": 1,
            "myTeamMonsterConditionMatchesNeeded": {
              "IsNotSummoned": 2
            }
          }
        }
      }
    },
    "passives": {
      "PlanAPassiveAElminaModernBoss": {
        "id": "PlanAPassiveAElminaModernBoss",
        "found": true,
        "localization": {
          "name": "Cyber Creations",
          "description": "This unit is not affected by stun effects.\n\nThis unit will gain a Charge each time it attacks and does not defeat any non-conjured enemies.\n\nWhen this unit enters battle:\n- If this unit is not conjured, it will have Hold Ground (If this unit would be defeated by an enemy attack or a status effect while having more than 1 HP, it instead survives with 1 HP).\n- If this unit is conjured, this unit will Endure the next damage that would defeat it with 1HP. Endure effects cannot stack.\n\nWhenever this unit defeats any number of non-conjured enemies with an attack:\n- An Elmina will be added to the front of allied reinforcements. This effect cannot trigger if there are 8 or more \"Elmina, Moonveiled Agent\" in the ally team.\n- Then all charges are removed from this unit.\n\nCertain skills are affected by and may consume charges. A unit can store up to 3 charges and all charges are removed from a unit that leaves the battlefield. All Elmina's created by this unit will have matching Levels, Limit Breaks, Awakenings, Boosts, Potential, Mastery, Weapons, and Accessories."
        }
      },
      "PlanBPassiveAElminaModernBoss": {
        "id": "PlanBPassiveAElminaModernBoss",
        "found": true,
        "localization": {
          "name": "Hyper Speed",
          "description": "Triggered the first time this unit takes damage from an attack and survives until after the end of the turn, and when this unit activates Elmina Unleashed:\n- All allies will be Purified (any negative status effects like sleep, burn or poison are removed).\n- Then all other ally units will be given the next turns by having their TU reduced. Active skills that grant turns cannot be used by those allies until after they have had the turn.\n\nThese effects will each only trigger once each time this unit is on the battlefield, and only if this unit entered the battlefield from reinforcements.\n\nEach time this unit damages at least one enemy with an attack and leaves them on or below 10% of max HP (even if they are defeated by the attack), this unit will get another turn. Damaged targets cannot trigger this effect again until TU advances.\n\nEffects that influence TU order may interrupt extra turns (e.g. Stuns targeting the lowest TU target)."
        }
      }
    },
    "activeSkillsAI": {},
    "aiSequence": null,
    "leaderCondition": null
  },
  "effect": null,
  "profile": null,
  "internal": {
    "sourceId": "ElminaModernBoss03",
    "family": "ElminaModernBoss",
    "source": "apk_extract",
    "treatAsDuplicateOf": null
  },
  "raw": {
    "name": "ElminaModernBoss03",
    "class": "Monster",
    "family": "ElminaModernBoss",
    "activeSkills": {
      "0": "DoubleAttackAElminaModernBoss",
      "1": "SuperModeAElminaModernBoss",
      "2": "StrongSingleAttackAElminaModernBoss",
      "3": "PushBackAElminaModernBoss"
    },
    "passives": {
      "0": "PlanAPassiveAElminaModernBoss",
      "1": "PlanBPassiveAElminaModernBoss"
    },
    "cost": 999,
    "baseAttack": 4000,
    "baseMaxHp": 178000,
    "speed": 498,
    "element": "Life",
    "weaponPref": "Hammer",
    "weaponPivotIndex": 0,
    "walkSound": "TestSound",
    "secure": 1,
    "aiTargetPickWeight": 1,
    "stars": 6,
    "evolvedStars": 6,
    "goldMultiplier": 1,
    "consolationMultiplier": 1,
    "battleOrbImageFlip": 0,
    "skillVoices": {
      "0": [
        1,
        2,
        3,
        4
      ],
      "1": [
        5,
        6,
        7,
        8
      ],
      "2": [
        9,
        10,
        11,
        12
      ],
      "3": [
        13,
        14,
        15,
        16
      ]
    },
    "damageVoices": [
      17,
      18,
      19,
      20
    ],
    "deathVoices": [
      21,
      22,
      23,
      24
    ]
  },
  "_build": {
    "scriptVersion": "6-character-family-states",
    "sourceHash": "5616af1cce1eba02507410389ec6513b4ac86ec2747fa0a9903a2c38305bdfa8",
    "dependencyHash": "41e791a6b1fcdcbb8915e11a05c5da7583cef69e5c2faf5fb211d6abf68a2551",
    "generatedAt": 1778218168
  }
}
